frontera_seedloader_mongodb/__init__.py
frontera_seedloader_mongodb/_version.py
frontera_seedloader_mongodb/contrib/__init__.py
frontera_seedloader_mongodb/contrib/scrapy/__init__.py
frontera_seedloader_mongodb/contrib/scrapy/middlewares/__init__.py
frontera_seedloader_mongodb/contrib/scrapy/middlewares/seeds/__init__.py
frontera_seedloader_mongodb/contrib/scrapy/middlewares/seeds/mongodb.py
frontera_seedloader_mongodb/contrib/scrapy/middlewares/seeds/mongodb_async.py
frontera_seedloader_mongodb/settings/__init__.py
frontera_seedloader_mongodb/settings/default_settings.py
frontera_seedloader_mongodb/utils/__init__.py
frontera_seedloader_mongodb/utils/get_mongodb_uri.py
frontera_seedloader_mongodb-0.0.6.dist-info/DESCRIPTION.rst
frontera_seedloader_mongodb-0.0.6.dist-info/METADATA
frontera_seedloader_mongodb-0.0.6.dist-info/RECORD
frontera_seedloader_mongodb-0.0.6.dist-info/WHEEL
frontera_seedloader_mongodb-0.0.6.dist-info/metadata.json
frontera_seedloader_mongodb-0.0.6.dist-info/top_level.txt
